[
  {
    "identifier": "DD2110402670007"
  },
  {
    "identifier": "TACW745120G0632"
  },
  {
    "identifier": "TPDC20210223036"
  },
  {
    "identifier": "TPDC20210223032"
  },
  {
    "identifier": "TPDC20210223002"
  },
  {
    "identifier": "TPDC20220360892"
  },
  {
    "identifier": "TPDC20210223001"
  },
  {
    "identifier": "TPDC20210223016"
  },
  {
    "identifier": "TPDC20210116004"
  },
  {
    "identifier": "TPDC20210116007"
  },
  {
    "identifier": "TPDC20210116005"
  },
  {
    "identifier": "TPDC20210223023"
  },
  {
    "identifier": "TPDC20210223010"
  },
  {
    "identifier": "TPDC20210116016"
  },
  {
    "identifier": "TPDC20210223020"
  },
  {
    "identifier": "TPDC20210223003"
  },
  {
    "identifier": "00140"
  },
  {
    "identifier": "00134"
  },
  {
    "identifier": "00184"
  },
  {
    "identifier": "00079"
  },
  {
    "identifier": "00147"
  },
  {
    "identifier": "00371"
  },
  {
    "identifier": "00066"
  },
  {
    "identifier": "00082"
  },
  {
    "identifier": "00140"
  },
  {
    "identifier": "00134"
  },
  {
    "identifier": "00184"
  },
  {
    "identifier": "00079"
  },
  {
    "identifier": "00147"
  },
  {
    "identifier": "00371"
  },
  {
    "identifier": "00066"
  },
  {
    "identifier": "00082"
  },
  {
    "identifier": "TPDC20210223025"
  },
  {
    "identifier": "TPDC20210116003"
  },
  {
    "identifier": "JDJ200300319W0"
  },
  {
    "identifier": "/TPDC20211260273"
  },
  {
    "identifier": "23R2130E0000851803"
  },
  {
    "identifier": "23R2150E00C0852479"
  },
  {
    "identifier": "23R2150E00C0852502"
  },
  {
    "identifier": "23R2150E00C0852488"
  },
  {
    "identifier": "DD2110402690005"
  },
  {
    "identifier": "DD2110402690003"
  },
  {
    "identifier": "TPDC20210223018"
  },
  {
    "identifier": "TPDC20210223022"
  },
  {
    "identifier": "//D72110382980011"
  },
  {
    "identifier": "23R2150E00C0852463"
  },
  {
    "identifier": "/EG119800001R0"
  },
  {
    "identifier": "TPDC20211260128"
  },
  {
    "identifier": "TPAC816"
  },
  {
    "identifier": "TPAC929"
  },
  {
    "identifier": "TPAC657"
  },
  {
    "identifier": "TPDC20220360894"
  },
  {
    "identifier": "TPDC2021228007"
  },
  {
    "identifier": "TPDC20220661108"
  },
  {
    "identifier": "TPDC2021228001A"
  },
  {
    "identifier": "23R2146E0000852322"
  },
  {
    "identifier": "23R2229E03A0850916"
  },
  {
    "identifier": "TPDC20220360893"
  },
  {
    "identifier": "/DD20513170I0180"
  },
  {
    "identifier": "TPDC20211260107"
  },
  {
    "identifier": "TACW740521G0312"
  },
  {
    "identifier": "23R2146E0000852295"
  },
  {
    "identifier": "TPAC708NEW"
  },
  {
    "identifier": "TPAC670NEW"
  },
  {
    "identifier": "TPAC714NEW"
  },
  {
    "identifier": "TPAC809NEW"
  },
  {
    "identifier": "23R2202E00C0850204"
  },
  {
    "identifier": "23R2150E00C0852471"
  },
  {
    "identifier": "TACW740521G0206"
  },
  {
    "identifier": "TPAC672"
  },
  {
    "identifier": "TPAC933NEW"
  },
  {
    "identifier": "23R2227E03A0850885"
  },
  {
    "identifier": "ZJ3200900010WE"
  },
  {
    "identifier": "TPAC2004"
  },
  {
    "identifier": "TPAC2008"
  },
  {
    "identifier": "23R2126E0000851774"
  },
  {
    "identifier": "23R2012E0003800509"
  },
  {
    "identifier": "TPDC20210224009"
  },
  {
    "identifier": "TPAC671"
  },
  {
    "identifier": "23R2150E00C0852499"
  },
  {
    "identifier": "D42210417640004"
  },
  {
    "identifier": "23R2202E00C0850035"
  },
  {
    "identifier": "23R2240E00C0850785"
  },
  {
    "identifier": "TACW742922G3077"
  },
  {
    "identifier": "23R2206E00C0850314"
  },
  {
    "identifier": "EG119900014R0"
  },
  {
    "identifier": "23R2240E00C0850773"
  },
  {
    "identifier": "TPDC20220260608NEW"
  },
  {
    "identifier": "TPAC111"
  },
  {
    "identifier": "TPAC174"
  },
  {
    "identifier": "00620"
  },
  {
    "identifier": "00619"
  },
  {
    "identifier": "TPAC1020"
  },
  {
    "identifier": "TPAC1005"
  },
  {
    "identifier": "JDJ201601216W0"
  },
  {
    "identifier": "TACW740521G0274"
  },
  {
    "identifier": "23R2206E00C0850251"
  },
  {
    "identifier": "JDJ201300910W0"
  },
  {
    "identifier": "TPAC020"
  },
  {
    "identifier": "TPAC388"
  },
  {
    "identifier": "23R2206E00C0850278"
  },
  {
    "identifier": "TACW740521G0274NEW"
  },
  {
    "identifier": "TPAC443"
  },
  {
    "identifier": "23R2142E0000852158"
  },
  {
    "identifier": "JDJ201601233W0"
  },
  {
    "identifier": "ZJ3201100043WE"
  },
  {
    "identifier": "ZJ3210400011WE"
  },
  {
    "identifier": "TACW745021G1539"
  },
  {
    "identifier": "TACW745021G1537"
  },
  {
    "identifier": "TACW744721G2448"
  },
  {
    "identifier": "TPAC229"
  },
  {
    "identifier": "23R2104E01A0851427"
  },
  {
    "identifier": "TACW745221G4558"
  },
  {
    "identifier": "DD1751321000001"
  },
  {
    "identifier": "00685"
  },
  {
    "identifier": "23R2120E0000851684"
  },
  {
    "identifier": "23R2002E01A0850005"
  },
  {
    "identifier": "23R2003E01A0850028"
  },
  {
    "identifier": "23R2003E01A0850027"
  },
  {
    "identifier": "EG119900026R0"
  },
  {
    "identifier": "23R2003E01A0850031"
  },
  {
    "identifier": "TACW742822G0198"
  },
  {
    "identifier": "23R2233E03A0851024"
  },
  {
    "identifier": "DD20513170I1022"
  },
  {
    "identifier": "23R2126E0000851766"
  },
  {
    "identifier": "TPAC345"
  },
  {
    "identifier": "DD2110402170005"
  },
  {
    "identifier": "TACW745221G4326"
  },
  {
    "identifier": "D12210407560003"
  },
  {
    "identifier": "TPAC161"
  },
  {
    "identifier": "TACW740521G0313"
  },
  {
    "identifier": "TACW742322G9493"
  },
  {
    "identifier": "23R2240E00C0850779"
  },
  {
    "identifier": "TPAC1093"
  },
  {
    "identifier": "TPAC025"
  },
  {
    "identifier": "//D12210407570008"
  },
  {
    "identifier": "23R2132E0000851868"
  },
  {
    "identifier": "TPAC731"
  },
  {
    "identifier": "TPAC739"
  },
  {
    "identifier": "TPAC664"
  },
  {
    "identifier": "TPAC740"
  },
  {
    "identifier": "TPAC732"
  },
  {
    "identifier": "TPAC719"
  },
  {
    "identifier": "TPAC667"
  },
  {
    "identifier": "TPAC668"
  },
  {
    "identifier": "TPAC1080"
  },
  {
    "identifier": "D82110388160001"
  },
  {
    "identifier": "ALB00025"
  },
  {
    "identifier": "TPAC1060"
  },
  {
    "identifier": "23R2146E03A5002335"
  },
  {
    "identifier": "23R2210E00C0850406"
  },
  {
    "identifier": "23R2210E00C0850402"
  },
  {
    "identifier": "/1347213800637"
  },
  {
    "identifier": "23R2150E00C0852482"
  },
  {
    "identifier": "23R2202E00C0850179"
  },
  {
    "identifier": "TPDC20220661010"
  },
  {
    "identifier": "DD2110402660010"
  },
  {
    "identifier": "TACW744721G2735"
  },
  {
    "identifier": "TACW745221G4325"
  },
  {
    "identifier": "TACW742922G3013"
  },
  {
    "identifier": "D82110387340006"
  },
  {
    "identifier": "TACW744721G2748"
  },
  {
    "identifier": "TPDC20220961533"
  },
  {
    "identifier": "TPDC20211019007"
  },
  {
    "identifier": "23R2150E00C0852484"
  },
  {
    "identifier": "23R2126E0000851773"
  },
  {
    "identifier": "DD2110402680008"
  },
  {
    "identifier": "/DD20513170I1002"
  },
  {
    "identifier": "23R2113E0003801528"
  },
  {
    "identifier": "23R2150E00C0852501"
  },
  {
    "identifier": "TML163553"
  },
  {
    "identifier": "DD2110402680009"
  },
  {
    "identifier": "23R2150E00C0852497"
  },
  {
    "identifier": "23R2150E00C0852466"
  },
  {
    "identifier": "DD2110402690001"
  },
  {
    "identifier": "23R2040E0000851193"
  },
  {
    "identifier": "TPDC20211260245"
  },
  {
    "identifier": "DD2110402170007"
  },
  {
    "identifier": "DD2110402170003"
  },
  {
    "identifier": "23R2233E03A0851113"
  },
  {
    "identifier": "23R2233E03A0851067"
  },
  {
    "identifier": "DD2110402690002"
  },
  {
    "identifier": "23R2150E00C0852458"
  },
  {
    "identifier": "EG119800005R0NEW"
  },
  {
    "identifier": "23R2230E00C0850724"
  },
  {
    "identifier": "23R2230E00C0850725"
  },
  {
    "identifier": "23R2150E00C0852486"
  },
  {
    "identifier": "23R2150E00C0852481"
  },
  {
    "identifier": "23R2150E00C0852503"
  },
  {
    "identifier": "ED819100001R0NEW"
  },
  {
    "identifier": "D42210417640001"
  },
  {
    "identifier": "0513160I0020"
  },
  {
    "identifier": "D42210417640002"
  },
  {
    "identifier": "ED819300017R0"
  },
  {
    "identifier": "23R2220E00C0850701"
  },
  {
    "identifier": "DD20513170I1071"
  },
  {
    "identifier": "23R2210E00C0850453"
  },
  {
    "identifier": "23R2230E00C0850770NEW"
  },
  {
    "identifier": "D12210407570001"
  },
  {
    "identifier": "DD20513170I0201NEW1"
  },
  {
    "identifier": "D12210407570002"
  },
  {
    "identifier": "DD20513170I1078"
  },
  {
    "identifier": "23R2230E00C0850746NEW"
  },
  {
    "identifier": "23R2220E00C0850698NEW"
  },
  {
    "identifier": "D12210407570003"
  },
  {
    "identifier": "DD20513170I1069"
  },
  {
    "identifier": "23R2230E00C0850732"
  },
  {
    "identifier": "23R2230E03A0850988"
  },
  {
    "identifier": "23R2049E0003801350"
  },
  {
    "identifier": "DD2110402680004"
  },
  {
    "identifier": "DD2110402690008"
  },
  {
    "identifier": "23R2220E00C0850699NEW"
  },
  {
    "identifier": "210407560010NEW"
  },
  {
    "identifier": "DD20513170I0202NEW"
  },
  {
    "identifier": "23R2233E03A0851122"
  },
  {
    "identifier": "ED819600037R0NEW"
  },
  {
    "identifier": "23R2020E0003800710"
  },
  {
    "identifier": "D42410509630003"
  },
  {
    "identifier": "TPAC065"
  },
  {
    "identifier": "00138"
  },
  {
    "identifier": "23R2116E0000851627"
  },
  {
    "identifier": "TPDC20210903003"
  },
  {
    "identifier": "/DD20513170I0179"
  },
  {
    "identifier": "00036"
  },
  {
    "identifier": "00043"
  },
  {
    "identifier": "TACW740521G0264"
  },
  {
    "identifier": "TPAC013"
  },
  {
    "identifier": "ED819300011R0"
  },
  {
    "identifier": "TPAC390"
  },
  {
    "identifier": "EG119900024R0"
  },
  {
    "identifier": "00130"
  },
  {
    "identifier": "23R2206E00C0850299"
  },
  {
    "identifier": "D12210407560005"
  },
  {
    "identifier": "EG119900009R0NEW"
  },
  {
    "identifier": "TPAC1224"
  },
  {
    "identifier": "23R2240E00C0850812"
  },
  {
    "identifier": "TPDC20220260564"
  },
  {
    "identifier": "TPDC20211003016NEW"
  },
  {
    "identifier": "23R2210E00C0850506"
  },
  {
    "identifier": "23R2229E03A0850948"
  },
  {
    "identifier": "23R2229E03A0850964"
  },
  {
    "identifier": "TACW740521G0318"
  },
  {
    "identifier": "TACW740521G0316"
  },
  {
    "identifier": "23R2202E00C0850186"
  },
  {
    "identifier": "23R2202E00C0850197"
  },
  {
    "identifier": "TACW740521G0271"
  },
  {
    "identifier": "TPDC20220661024"
  },
  {
    "identifier": "TACW742322G0854"
  },
  {
    "identifier": "TPAC125"
  },
  {
    "identifier": "23R2142E0000852159"
  },
  {
    "identifier": "ED819600031R0"
  },
  {
    "identifier": "TPDC20211260072"
  },
  {
    "identifier": "ALB00078"
  },
  {
    "identifier": "23R2126E0000851762"
  },
  {
    "identifier": "23R2229E03A0850954"
  },
  {
    "identifier": "TPAC144"
  },
  {
    "identifier": "23R2227E03A0850829"
  },
  {
    "identifier": "S0224DC000475"
  },
  {
    "identifier": "TPDC20211260089"
  },
  {
    "identifier": "00512"
  },
  {
    "identifier": "23R2227E03A0850848"
  },
  {
    "identifier": "ALB00134"
  },
  {
    "identifier": "23R2137E0000851999"
  },
  {
    "identifier": "D62210428520008"
  },
  {
    "identifier": "TPDC20211160060"
  },
  {
    "identifier": "TPAC004"
  },
  {
    "identifier": "TPDC12345"
  },
  {
    "identifier": "TPAC855"
  },
  {
    "identifier": "ALB00125"
  },
  {
    "identifier": "23R2048E03A5001297"
  },
  {
    "identifier": "TPAC491"
  },
  {
    "identifier": "TPAC529"
  },
  {
    "identifier": "TPAC1142"
  },
  {
    "identifier": "ALB00127"
  },
  {
    "identifier": "23R2202E00C0850135"
  },
  {
    "identifier": "TPDC20220260784"
  },
  {
    "identifier": "TPAC201"
  },
  {
    "identifier": "TELLUS74"
  },
  {
    "identifier": "JDJ194800433W0"
  },
  {
    "identifier": "TPDC20211003071"
  },
  {
    "identifier": "TPAC130"
  },
  {
    "identifier": "23R2116E0003801530"
  },
  {
    "identifier": "TELLUS60"
  },
  {
    "identifier": "TPAC1015NEW"
  },
  {
    "identifier": "23R2150E00C0852464NEW"
  },
  {
    "identifier": "1347212300209"
  },
  {
    "identifier": "TPAC1019"
  },
  {
    "identifier": "TACW740521G0181"
  },
  {
    "identifier": "TELLUS30"
  },
  {
    "identifier": "23R2228E03A0850914"
  },
  {
    "identifier": "23R2142E0000852192"
  },
  {
    "identifier": "TPAC132"
  },
  {
    "identifier": "TPAC039"
  },
  {
    "identifier": "TPDC20211160036NEW"
  },
  {
    "identifier": "DD20513170I0203"
  },
  {
    "identifier": "DD2110402690006"
  },
  {
    "identifier": "TPDC20210224010"
  },
  {
    "identifier": "23R2206E00C0850308"
  },
  {
    "identifier": "TPAC1037"
  },
  {
    "identifier": "D12210407570004"
  },
  {
    "identifier": "0513160I0023"
  },
  {
    "identifier": "TPAC119"
  },
  {
    "identifier": "23R2130E0000851818"
  },
  {
    "identifier": "23R2145E0000852257"
  },
  {
    "identifier": "23R2145E0000852272"
  },
  {
    "identifier": "TPDC20210831002NEW"
  },
  {
    "identifier": "TPDC20211260244"
  },
  {
    "identifier": "23R2146E0000852310"
  },
  {
    "identifier": "23R2202E00C0850062"
  },
  {
    "identifier": "23R2150E00C0852490"
  },
  {
    "identifier": "23R2150E00C0852494"
  },
  {
    "identifier": "23R2150E00C0852500"
  },
  {
    "identifier": "23R2202E00C0850061"
  },
  {
    "identifier": "DD2110402670010"
  },
  {
    "identifier": "23R2150E00C0852491"
  },
  {
    "identifier": "23R2150E00C0852506"
  },
  {
    "identifier": "D52410513890006"
  },
  {
    "identifier": "23R2126E0000851772"
  },
  {
    "identifier": "ZJ3201200086WE"
  },
  {
    "identifier": "JDJ201300827W0"
  },
  {
    "identifier": "23R2150E00C0852498"
  },
  {
    "identifier": "23R2210E00C0850446"
  },
  {
    "identifier": "/TPDC20220260460NEW"
  },
  {
    "identifier": "00492"
  },
  {
    "identifier": "23R2308E03A0851174"
  },
  {
    "identifier": "23R2137E0000851989"
  },
  {
    "identifier": "00558"
  },
  {
    "identifier": "OVN20047"
  },
  {
    "identifier": "TPDC20210831019"
  },
  {
    "identifier": "TPAC679NEW"
  },
  {
    "identifier": "TPAC1161NEW"
  },
  {
    "identifier": "TPAC448NEW"
  },
  {
    "identifier": "TPAC006NEW"
  },
  {
    "identifier": "TPAC021NEW"
  },
  {
    "identifier": "TPAC022NEW"
  },
  {
    "identifier": "DD2110402680001"
  },
  {
    "identifier": "DD2110402660001"
  },
  {
    "identifier": "TPAC1087"
  },
  {
    "identifier": "TPAC651"
  },
  {
    "identifier": "TPAC024NEW1"
  },
  {
    "identifier": "TPAC930NEW"
  },
  {
    "identifier": "TPAC196NEW"
  },
  {
    "identifier": "TPAC730NEW"
  },
  {
    "identifier": "TPAC278NEW"
  },
  {
    "identifier": "TPAC264NEW1"
  },
  {
    "identifier": "TPAC431NEW"
  },
  {
    "identifier": "TPAC215NEW"
  },
  {
    "identifier": "TPAC290NEW"
  },
  {
    "identifier": "D72110382980010NEW/"
  },
  {
    "identifier": "TPAC743"
  },
  {
    "identifier": "ACHBDCC03250118"
  },
  {
    "identifier": "ACHBDCC03250472"
  },
  {
    "identifier": "KZM020102F4"
  },
  {
    "identifier": "00258"
  },
  {
    "identifier": "00373"
  },
  {
    "identifier": "00583"
  },
  {
    "identifier": "TPAC263NEW"
  },
  {
    "identifier": "TPAC436NEW"
  },
  {
    "identifier": "TPAC273NEW"
  },
  {
    "identifier": "TPAC332NEW"
  },
  {
    "identifier": "TPAC656"
  },
  {
    "identifier": "TPAC906"
  },
  {
    "identifier": "TPAC950"
  },
  {
    "identifier": "TPDC20211260269"
  },
  {
    "identifier": "TPAC744"
  },
  {
    "identifier": "TPAC662"
  },
  {
    "identifier": "TPAC949"
  },
  {
    "identifier": "TPAC918"
  },
  {
    "identifier": "TPAC915"
  },
  {
    "identifier": "TPAC830"
  },
  {
    "identifier": "TPAC909"
  },
  {
    "identifier": "TPAC851"
  },
  {
    "identifier": "TPAC748"
  },
  {
    "identifier": "TPAC814"
  },
  {
    "identifier": "TPAC683"
  },
  {
    "identifier": "TPAC750"
  },
  {
    "identifier": "TPAC808"
  },
  {
    "identifier": "TPAC676"
  },
  {
    "identifier": "TPAC923"
  },
  {
    "identifier": "TPAC852"
  },
  {
    "identifier": "1347213100358"
  },
  {
    "identifier": "ST1911"
  },
  {
    "identifier": "DD20513170I1018"
  },
  {
    "identifier": "23R2028E0000851045"
  },
  {
    "identifier": "TPAC805"
  },
  {
    "identifier": "TWBCEHU13723012NEW"
  },
  {
    "identifier": "D72210431460001"
  },
  {
    "identifier": "ALB00074"
  },
  {
    "identifier": "ACHBDCC03250521"
  },
  {
    "identifier": "DD2110402660004"
  },
  {
    "identifier": "TPDC20210725018"
  },
  {
    "identifier": "23R2011E01A0850500"
  },
  {
    "identifier": "TACW744721G2739"
  },
  {
    "identifier": "D52310474470055"
  },
  {
    "identifier": "23R2137E0000852020"
  },
  {
    "identifier": "TACW740521G0158NEW"
  },
  {
    "identifier": "DN2210447350008"
  },
  {
    "identifier": "TPAC934"
  },
  {
    "identifier": "TPAC2026"
  },
  {
    "identifier": "23R2137E0000851985NEW"
  },
  {
    "identifier": "TPAC242"
  },
  {
    "identifier": "23R2210E00C0850530"
  },
  {
    "identifier": "TPDC20220260809"
  },
  {
    "identifier": "TPDCD24030167"
  },
  {
    "identifier": "TPDCD24030172"
  },
  {
    "identifier": "TPDC20220260481NEW"
  },
  {
    "identifier": "TPAC1220NEW"
  },
  {
    "identifier": "TPDC20220260650"
  },
  {
    "identifier": "TPDC20220260519"
  },
  {
    "identifier": "KZM0101012B"
  },
  {
    "identifier": "ED819600035R0NEW"
  },
  {
    "identifier": "DD20513170I1025"
  },
  {
    "identifier": "KZM01010127"
  },
  {
    "identifier": "23R2202E00C0850207"
  },
  {
    "identifier": "23R2146E03A5002336"
  },
  {
    "identifier": "TPAC1194"
  },
  {
    "identifier": "23R2240E00C0850783"
  },
  {
    "identifier": "TPAC294"
  },
  {
    "identifier": "TPDC20210421002"
  },
  {
    "identifier": "23R2003E0000850016NEW"
  },
  {
    "identifier": "TACW744721G2684"
  },
  {
    "identifier": "D12010310600017"
  },
  {
    "identifier": "23R2150E00C0852530"
  },
  {
    "identifier": "DN2210447350004"
  },
  {
    "identifier": "TPDC20220260763"
  },
  {
    "identifier": "TPAC488"
  },
  {
    "identifier": "23R2219E01A0850001"
  },
  {
    "identifier": "23R2221E03A5000002"
  },
  {
    "identifier": "TPAC831"
  },
  {
    "identifier": "TPAC932"
  },
  {
    "identifier": "TPAC812"
  },
  {
    "identifier": "TPAC665"
  },
  {
    "identifier": "TPDC20220761261"
  },
  {
    "identifier": "TPDC20211003019"
  },
  {
    "identifier": "ACHBDCC03250106"
  },
  {
    "identifier": "D12010310600015"
  },
  {
    "identifier": "TPDC20220961515"
  },
  {
    "identifier": "23R2049E0003801377NEW"
  },
  {
    "identifier": "TPDC20211003080"
  },
  {
    "identifier": "TPAC937"
  },
  {
    "identifier": "TPAC351"
  },
  {
    "identifier": "TPAC734"
  },
  {
    "identifier": "TPAC729"
  },
  {
    "identifier": "TPAC1025"
  },
  {
    "identifier": "TPAC738"
  },
  {
    "identifier": "TPAC726"
  },
  {
    "identifier": "23R2032E03A5001078"
  },
  {
    "identifier": "23R2142E0000852167NEW"
  },
  {
    "identifier": "23R2240E00C0850777"
  },
  {
    "identifier": "TPDC20211260097"
  },
  {
    "identifier": "TPDC20210903014"
  },
  {
    "identifier": "TPDC20210831023NEW"
  },
  {
    "identifier": "TPDC20211003022"
  },
  {
    "identifier": "ZJ3191900018WENEW"
  },
  {
    "identifier": "23R2130E0000851813"
  },
  {
    "identifier": "TPDC162651"
  },
  {
    "identifier": "TPDC163915"
  },
  {
    "identifier": "ACHBDCC03250269"
  },
  {
    "identifier": "ACHBDCC03250265"
  },
  {
    "identifier": "TACW740521G0330"
  },
  {
    "identifier": "ZJ3200900019WE"
  },
  {
    "identifier": "23R2028E0000851043"
  },
  {
    "identifier": "TPAC371NEW"
  },
  {
    "identifier": "TPDC20211019029NEW1"
  },
  {
    "identifier": "KZM02010296"
  },
  {
    "identifier": "TPDC20220761213"
  },
  {
    "identifier": "23R2202E03A1KV0240"
  },
  {
    "identifier": "D82110387600002"
  },
  {
    "identifier": "TPAC073"
  },
  {
    "identifier": "TPAC839"
  },
  {
    "identifier": "TPDC20211019008NEW"
  },
  {
    "identifier": "TPDC20210421003"
  },
  {
    "identifier": "ED819300009R0"
  },
  {
    "identifier": "TPDC20220260673"
  },
  {
    "identifier": "TPAC1068"
  },
  {
    "identifier": "TPDC20210903010NEW"
  },
  {
    "identifier": "TPDC20210903019"
  },
  {
    "identifier": "23R2233E03A0851060NEW"
  },
  {
    "identifier": "ALB00177NEW"
  },
  {
    "identifier": "23R2150E00C0852505"
  },
  {
    "identifier": "23R2142E0000852161"
  },
  {
    "identifier": "23R2120E0000851688"
  },
  {
    "identifier": "TPDC201912005"
  },
  {
    "identifier": "JDJ200300315W0"
  },
  {
    "identifier": "00487"
  },
  {
    "identifier": "23R2233E03A0851071"
  },
  {
    "identifier": "TPDC20211003055NEW"
  },
  {
    "identifier": "TWBCEHU13920020"
  },
  {
    "identifier": "TPDC20211003057"
  },
  {
    "identifier": "23R2142E0000852163"
  },
  {
    "identifier": "TPDC20220260559"
  },
  {
    "identifier": "23R2202E00C0850069"
  },
  {
    "identifier": "23R2139E01A0850009"
  },
  {
    "identifier": "TPAC1122"
  },
  {
    "identifier": "ACHBDCC03250110"
  },
  {
    "identifier": "TPDC20220260467NEW"
  },
  {
    "identifier": "TPDC20211260156"
  },
  {
    "identifier": "00594"
  },
  {
    "identifier": "1513160I0017"
  },
  {
    "identifier": "D72110382980004NEW"
  },
  {
    "identifier": "D72110382980006NEW"
  },
  {
    "identifier": "D22110359130007NEW"
  },
  {
    "identifier": "D72110382980010NEW"
  },
  {
    "identifier": "D22110359130006NEW"
  },
  {
    "identifier": "D72110382980011NEW"
  },
  {
    "identifier": "D72110382980008NEW"
  },
  {
    "identifier": "D22110359130003NEW"
  },
  {
    "identifier": "D72110382980009NEW"
  },
  {
    "identifier": "D72110382980007NEW"
  },
  {
    "identifier": "23R2142E0000852198NEW"
  },
  {
    "identifier": "TPAC191"
  },
  {
    "identifier": "23R2142E0000852162NEW"
  },
  {
    "identifier": "23R2139E01A0850002"
  },
  {
    "identifier": "TPDC20220260789"
  },
  {
    "identifier": "DD2210455770001"
  },
  {
    "identifier": "DN2210447350002"
  },
  {
    "identifier": "S0224DC000473"
  },
  {
    "identifier": "D22310462580001"
  },
  {
    "identifier": "23R2116E0000851631NEW"
  },
  {
    "identifier": "23R2150E00C0852480NEW"
  },
  {
    "identifier": "TPDC162645"
  },
  {
    "identifier": "TPDC20220661056"
  },
  {
    "identifier": "00551"
  },
  {
    "identifier": "23R2202E00C0850135NEW"
  },
  {
    "identifier": "TPDC20220260729"
  },
  {
    "identifier": "23R2202E00C0850007NEW"
  },
  {
    "identifier": "TPDC20211160043NEW"
  },
  {
    "identifier": "TPDC20211003092"
  },
  {
    "identifier": "TPDC20220260705"
  },
  {
    "identifier": "00298"
  },
  {
    "identifier": "TPAC723"
  },
  {
    "identifier": "23R2110E0000851477NEW"
  },
  {
    "identifier": "LB25062131"
  },
  {
    "identifier": "TPAC1218"
  },
  {
    "identifier": "TPAC1153"
  },
  {
    "identifier": "TPDC20220260546"
  },
  {
    "identifier": "D62210428520016"
  },
  {
    "identifier": "23R2146E0000852316NEW"
  },
  {
    "identifier": "TPDC20220260496"
  },
  {
    "identifier": "23R2210E00C0850435"
  },
  {
    "identifier": "ACHBDCC03250533"
  },
  {
    "identifier": "TPDC20220260583"
  },
  {
    "identifier": "TPAC1039"
  },
  {
    "identifier": "TCACDSS33015"
  },
  {
    "identifier": "TPDC20220761224"
  },
  {
    "identifier": "TPDC20211260075"
  },
  {
    "identifier": "TPAC183"
  },
  {
    "identifier": "ZJ3191900062WE"
  },
  {
    "identifier": "TPDC20220260757"
  },
  {
    "identifier": "23R2230E00C0850722"
  },
  {
    "identifier": "TPDC20220260645"
  },
  {
    "identifier": "TACW744721G2455"
  },
  {
    "identifier": "23R2130E0000851812"
  },
  {
    "identifier": "TACW745221G4365"
  },
  {
    "identifier": "TPDC20220260832NEW"
  },
  {
    "identifier": "DD1751321000008"
  },
  {
    "identifier": "TPAC417NEW"
  },
  {
    "identifier": "D52410514130017"
  },
  {
    "identifier": "23R2210E00C0850403"
  }
]